{
  "success": false,
  "method": "addin",
  "reason": "Dimension Engine v3 无新增尺寸（所有策略受 SW2025 API 限制）",
  "timestamp": "2026-06-20 14:12:26",
  "engine_version": "v3.0",
  "drawing_path": "C:\\Users\\Vision\\Desktop\\SW 相关\\3D转2D测试图纸\\LB26001-A-04-007.SLDDRW",
  "part_path": "C:\\Users\\Vision\\Desktop\\SW 相关\\3D转2D测试图纸\\LB26001-A-04-007.SLDPRT",
  "run_dir": "C:\\Users\\Vision\\Desktop\\SW 相关\\drw_output\\runs\\v21_007_1781935946",
  "policy": {
    "part_class": "feature_part",
    "dimension_policy": "full",
    "required_dims": "[\"overall_length"
  },
  "dim_before": 8,
  "dim_after": 8,
  "existing_display_dim_count": 8,
  "addin_created_dim_count": 0,
  "model_associative_dim_count": 0,
  "note_dim_count": 0,
  "standard_annotation_count": 0,
  "strategy_log": [
    {
      "strategy": "1_import_pmi_dimxpert",
      "count": 0,
      "success": false,
      "reason": "模型无 PMI/DimXpert 注解"
    },
    {
      "action": "strategy2_no_lines",
      "view": "工程图视图1",
      "line_count": 0
    },
    {
      "action": "strategy2_no_lines",
      "view": "工程图视图2",
      "line_count": 0
    },
    {
      "action": "strategy2_no_lines",
      "view": "工程图视图3",
      "line_count": 0
    },
    {
      "strategy": "2_auto_dimension",
      "count": 0,
      "success": false,
      "reason": "GetLines2+AddDimension5 无法创建尺寸（SW2025 限制：SelectByID2 无法选中 drawing view 中的边）"
    },
    {
      "strategy": "3_visible_entity_dimension",
      "count": 0,
      "success": false,
      "reason": "GetLines2 无可用线段或 AddDimension5 失败"
    },
    {
      "strategy": "4_pmi_seed_copied_model",
      "count": 0,
      "success": false,
      "reason": "PMI Seed 未创建尺寸: OpenDoc6/OpenDoc5/OpenDoc 副本均返回 null",
      "seed_details": {
        "engine_version": "v3.1",
        "timestamp": "2026-06-20 14:12:27",
        "original_part_path": "C:\\Users\\Vision\\Desktop\\SW 相关\\3D转2D测试图纸\\LB26001-A-04-007.SLDPRT",
        "original_was_open": false,
        "seed_part_path": "C:\\Temp\\SwAddin\\seed_parts\\LB26001-A-04-007_seed.SLDPRT",
        "opendoc6_error": "returned null",
        "opendoc6_errors_code": 65536,
        "opendoc6_warnings_code": 0,
        "opendoc5_error": "未知名称。 (异常来自 HRESULT:0x80020006 (DISP_E_UNKNOWNNAME))",
        "opendoc_error": "调用的目标发生了异常。",
        "success": false,
        "reason": "OpenDoc6/OpenDoc5/OpenDoc 副本均返回 null"
      }
    }
  ],
  "saved": false,
  "step": "done"
}