{
  "schema": "sw_drawing_studio.reference_metrics.v1",
  "source": "csharp_sidecar",
  "generated_at": "2026-06-22 18:13:46",
  "path": "C:\\Users\\Vision\\Desktop\\SW 相关\\3D转2D测试图纸\\LB26001-A-04-035.SLDDRW",
  "exists": true,
  "success": true,
  "status": "ok",
  "reason": "",
  "connection_method": "get_active_object",
  "sw_revision": "33.5.0",
  "open_errors": 0,
  "open_warnings": 0,
  "sheet": {
    "name": null,
    "paper_size": [],
    "properties": [
      6,
      13,
      2,
      1,
      1,
      0.297,
      0.21,
      1
    ]
  },
  "view_count": 4,
  "view_types": {
    "7": 1,
    "4": 3
  },
  "view_names": [
    "工程图视图1",
    "工程图视图2",
    "工程图视图3",
    "工程图视图4"
  ],
  "view_outlines": [
    {
      "name": "工程图视图1",
      "type": "7",
      "outline": [
        0.05646355670103086,
        0.1140420096478826,
        0.10386355670103087,
        0.18457783571294212
      ]
    },
    {
      "name": "工程图视图2",
      "type": "4",
      "outline": [
        0.05646355670103086,
        0.06001065721649471,
        0.10386355670103087,
        0.08441065721649492
      ]
    },
    {
      "name": "工程图视图3",
      "type": "4",
      "outline": [
        0.1489030154639174,
        0.1140420096478826,
        0.17330301546391755,
        0.18457783571294212
      ]
    },
    {
      "name": "工程图视图4",
      "type": "4",
      "outline": [
        0.19565127743489563,
        0.05623038344878579,
        0.24294215040015577,
        0.13781804438626574
      ]
    }
  ],
  "display_dim_count": 11,
  "annotation_count": 0,
  "file_size_bytes": 371553,
  "warnings": [],
  "sidecar_report": "C:\\Users\\Vision\\Desktop\\SW 相关\\drw_output\\reference_metrics_sidecar\\LB26001-A-04-035_reference.json",
  "returncode": 0,
  "stdout": "{\"success\":true,\"status\":\"ok\",\"out\":\"C:\\\\Users\\\\Vision\\\\Desktop\\\\SW 相关\\\\drw_output\\\\reference_metrics_sidecar\\\\LB26001-A-04-035_reference.json\",\"view_count\":4,\"display_dim_count\":11}",
  "stderr": "",
  "annotation_probe": {
    "source": "pywin32_annotation_probe",
    "success": true,
    "reason": "",
    "view_count": 5,
    "display_dim_count": 11,
    "display_dim_annotation_count": 0,
    "display_dim_count_source": "annotation_type1",
    "annotation_count": 0,
    "open_errors": 0,
    "open_warnings": 128
  },
  "annotation_probe_report": "C:\\Users\\Vision\\Desktop\\SW 相关\\drw_output\\reference_metrics_sidecar\\LB26001-A-04-035_reference_annotation_probe.json",
  "display_dim_annotation_count": 0,
  "display_dim_count_source": "display_dimension_api"
}